avroconvert/__init__.py
avroconvert/avroconvert.py
avroconvert/cli.py
avroconvert/execute.py
avroconvert/log_source.py
avroconvert/sources/__init__.py
avroconvert/sources/filesystem/__init__.py
avroconvert/sources/filesystem/reader.py
avroconvert/sources/gcs/__init__.py
avroconvert/sources/gcs/reader.py
avroconvert/sources/s3/__init__.py
avroconvert/sources/s3/reader.py
avroconvert-0.1.1.dist-info/AUTHORS.rst
avroconvert-0.1.1.dist-info/LICENSE
avroconvert-0.1.1.dist-info/METADATA
avroconvert-0.1.1.dist-info/WHEEL
avroconvert-0.1.1.dist-info/entry_points.txt
avroconvert-0.1.1.dist-info/top_level.txt
avroconvert-0.1.1.dist-info/RECORD
