Metadata-Version: 2.1
Name: avroconvert
Version: 0.1.1
Summary: Utility to convert avro files to csv, json and parquet formats
Home-page: https://github.com/shrinivdeshmukh/avroconvert
Author: Shrinivas Vijay Deshmukh
Author-email: shrinivas.deshmukh11@gmail.com
License: MIT license
Keywords: avroconvert
Platform: UNKNOWN
Classifier: Development Status :: 2 - Pre-Alpha
Classifier: Intended Audience :: Developers
Classifier: License :: OSI Approved :: MIT License
Classifier: Natural Language :: English
Classifier: Programming Language :: Python :: 3
Classifier: Programming Language :: Python :: 3.6
Classifier: Programming Language :: Python :: 3.7
Classifier: Programming Language :: Python :: 3.8
Requires-Python: >=3.6
Requires-Dist: boto3 (==1.15.15)
Requires-Dist: fastavro (==1.0.0.post1)
Requires-Dist: pandas (==1.2.0)
Requires-Dist: pyarrow (==4.0.1)
Requires-Dist: google-api-core (==1.22.4)
Requires-Dist: google-api-python-client (==1.12.8)
Requires-Dist: google-auth (==1.22.1)
Requires-Dist: google-auth-httplib2 (==0.0.4)
Requires-Dist: google-auth-oauthlib (==0.4.2)
Requires-Dist: google-cloud-bigquery (==2.0.0)
Requires-Dist: google-cloud-bigquery-storage (==2.0.0)
Requires-Dist: google-cloud-core (==1.4.2)
Requires-Dist: google-cloud-storage (==1.31.2)
Requires-Dist: google-crc32c (==1.0.0)
Requires-Dist: google-resumable-media (==1.1.0)
Requires-Dist: googleapis-common-protos (==1.52.0)
Requires-Dist: pydata-google-auth (==1.1.0)
Requires-Dist: python-snappy (==0.6.0)
